setup.py
PirxcySurvey/__init__.py
PirxcySurvey/_colors.py
PirxcySurvey/_constants.py
PirxcySurvey/_controls.py
PirxcySurvey/_funnels.py
PirxcySurvey/_graphics.py
PirxcySurvey/_handle.py
PirxcySurvey/_helpers.py
PirxcySurvey/_mutates.py
PirxcySurvey/_printers.py
PirxcySurvey/_routines.py
PirxcySurvey/_searches.py
PirxcySurvey/_stage.py
PirxcySurvey/_system.py
PirxcySurvey/_theme.py
PirxcySurvey/_utils.py
PirxcySurvey/_visuals.py
PirxcySurvey/_widgets.py
PirxcySurvey.egg-info/PKG-INFO
PirxcySurvey.egg-info/SOURCES.txt
PirxcySurvey.egg-info/dependency_links.txt
PirxcySurvey.egg-info/top_level.txt