Metadata-Version: 1.2
Name: PirxcySurvey
Version: 0.0.1
Summary: Survey package fixed for exe!
Home-page: UNKNOWN
Author: pirxcy
License: UNKNOWN
Platform: UNKNOWN
Classifier: Programming Language :: Python :: 3
Classifier: License :: OSI Approved :: MIT License
Classifier: Operating System :: OS Independent
Requires-Python: >=3.10
